MANIFEST.in
setup.py
docs/QuickStart.md
docs/index.html
mkdocs_juice.egg-info/.DS_Store
mkdocs_juice.egg-info/PKG-INFO
mkdocs_juice.egg-info/SOURCES.txt
mkdocs_juice.egg-info/dependency_links.txt
mkdocs_juice.egg-info/entry_points.txt
mkdocs_juice.egg-info/not-zip-safe
mkdocs_juice.egg-info/top_level.txt
theme/__init__.py
theme/base.html
theme/nav.html
theme/search.html
theme/css/bootstrap-theme.min.css
theme/css/bootstrap.min.css
theme/css/theme.css
theme/fonts/glyphicons-halflings-regular.eot
theme/fonts/glyphicons-halflings-regular.svg
theme/fonts/glyphicons-halflings-regular.ttf
theme/fonts/glyphicons-halflings-regular.woff
theme/include/footer.html
theme/include/head.html
theme/include/toc.html
theme/js/bootstrap.min.js
theme/js/ie-emulation-modes-warning.js
theme/js/ie10-viewport-bug-workaround.js
theme/js/theme.js