Metadata-Version: 1.0
Name: mkdocs-juice
Version: 1.0.1
Summary: This is a theme of mkdocs
Home-page: https://github.com/Dxtan/mkdocs-juice
Author: Dxtan
Author-email: dxtan@icloud.com
License: MIT
Platform: UNKNOWN
